chessbots/__init__.py
chessbots/bot.py
chessbots/engine.py
chessbots-0.2.0.dist-info/LICENSE
chessbots-0.2.0.dist-info/METADATA
chessbots-0.2.0.dist-info/WHEEL
chessbots-0.2.0.dist-info/top_level.txt
chessbots-0.2.0.dist-info/RECORD
