Metadata-Version: 2.1
Name: chessbots
Version: 0.2.0
Summary: Package for chess bots
Home-page: https://github.com/JeniaD/chessbots
Author: JeniaD
Author-email: jeniadeshchenko@gmail.com
License: UNKNOWN
Project-URL: Bug Tracker, https://github.com/JeniaD/chessbots/issues
Platform: UNKNOWN
Classifier: Programming Language :: Python :: 3
Classifier: License :: OSI Approved :: MIT License
Classifier: Operating System :: OS Independent
Requires-Python: >=3.6
License-File: LICENSE
Requires-Dist: chess (==1.8.0)
